odoo9_addon_mgmtsystem_claim-9.0.1.1.1.99.dev38-py3.8-nspkg.pth
odoo_addons/mgmtsystem_claim/__init__.py
odoo_addons/mgmtsystem_claim/__openerp__.py
odoo_addons/mgmtsystem_claim/workflow_mgmtsystem_claim.xml
odoo_addons/mgmtsystem_claim/data/claim_sequence.xml
odoo_addons/mgmtsystem_claim/data/mgmtsystem_claim_stage.xml
odoo_addons/mgmtsystem_claim/i18n/am.po
odoo_addons/mgmtsystem_claim/i18n/ar.po
odoo_addons/mgmtsystem_claim/i18n/bg.po
odoo_addons/mgmtsystem_claim/i18n/bs.po
odoo_addons/mgmtsystem_claim/i18n/ca.po
odoo_addons/mgmtsystem_claim/i18n/ca_ES.po
odoo_addons/mgmtsystem_claim/i18n/cs.po
odoo_addons/mgmtsystem_claim/i18n/da.po
odoo_addons/mgmtsystem_claim/i18n/da_DK.po
odoo_addons/mgmtsystem_claim/i18n/de.po
odoo_addons/mgmtsystem_claim/i18n/el_GR.po
odoo_addons/mgmtsystem_claim/i18n/en_GB.po
odoo_addons/mgmtsystem_claim/i18n/es.po
odoo_addons/mgmtsystem_claim/i18n/es_AR.po
odoo_addons/mgmtsystem_claim/i18n/es_CL.po
odoo_addons/mgmtsystem_claim/i18n/es_CO.po
odoo_addons/mgmtsystem_claim/i18n/es_CR.po
odoo_addons/mgmtsystem_claim/i18n/es_DO.po
odoo_addons/mgmtsystem_claim/i18n/es_EC.po
odoo_addons/mgmtsystem_claim/i18n/es_ES.po
odoo_addons/mgmtsystem_claim/i18n/es_MX.po
odoo_addons/mgmtsystem_claim/i18n/es_PE.po
odoo_addons/mgmtsystem_claim/i18n/es_PY.po
odoo_addons/mgmtsystem_claim/i18n/es_VE.po
odoo_addons/mgmtsystem_claim/i18n/et.po
odoo_addons/mgmtsystem_claim/i18n/eu.po
odoo_addons/mgmtsystem_claim/i18n/fa.po
odoo_addons/mgmtsystem_claim/i18n/fi.po
odoo_addons/mgmtsystem_claim/i18n/fr.po
odoo_addons/mgmtsystem_claim/i18n/fr_CA.po
odoo_addons/mgmtsystem_claim/i18n/fr_CH.po
odoo_addons/mgmtsystem_claim/i18n/fr_FR.po
odoo_addons/mgmtsystem_claim/i18n/gl.po
odoo_addons/mgmtsystem_claim/i18n/gl_ES.po
odoo_addons/mgmtsystem_claim/i18n/he.po
odoo_addons/mgmtsystem_claim/i18n/hr.po
odoo_addons/mgmtsystem_claim/i18n/hr_HR.po
odoo_addons/mgmtsystem_claim/i18n/hu.po
odoo_addons/mgmtsystem_claim/i18n/id.po
odoo_addons/mgmtsystem_claim/i18n/it.po
odoo9_addon_mgmtsystem_claim-9.0.1.1.1.99.dev38.dist-info/METADATA
odoo9_addon_mgmtsystem_claim-9.0.1.1.1.99.dev38.dist-info/WHEEL
odoo9_addon_mgmtsystem_claim-9.0.1.1.1.99.dev38.dist-info/namespace_packages.txt
odoo9_addon_mgmtsystem_claim-9.0.1.1.1.99.dev38.dist-info/top_level.txt
odoo9_addon_mgmtsystem_claim-9.0.1.1.1.99.dev38.dist-info/RECORD
